locobuzz_protocol_buffer_python/__init__.py
locobuzz_protocol_buffer_python/compile_protos.cp311-win_amd64.pyd
locobuzz_protocol_buffer_python/compile_protos.py
locobuzz_protocol_buffer_python/deserialize_protobuf.cp311-win_amd64.pyd
locobuzz_protocol_buffer_python/deserialize_protobuf.py
locobuzz_protocol_buffer_python/json_to_protobuf.cp311-win_amd64.pyd
locobuzz_protocol_buffer_python/json_to_protobuf.py
locobuzz_protocol_buffer_python/protocol_to_json.cp311-win_amd64.pyd
locobuzz_protocol_buffer_python/protocol_to_json.py
locobuzz_protocol_buffer_python/serialize_message.cp311-win_amd64.pyd
locobuzz_protocol_buffer_python/serialize_message.py
locobuzz_protocol_buffer_python/utilities.cp311-win_amd64.pyd
locobuzz_protocol_buffer_python/utilities.py
locobuzz_protocol_buffer_python/grpc/__init__.py
locobuzz_protocol_buffer_python/grpc/generated/__init__.py
locobuzz_protocol_buffer_python/grpc/generated/quora_data_pb2.cp311-win_amd64.pyd
locobuzz_protocol_buffer_python/grpc/generated/quora_data_pb2.py
locobuzz_protocol_buffer_python/grpc/generated/quora_data_pb2_grpc.cp311-win_amd64.pyd
locobuzz_protocol_buffer_python/grpc/generated/quora_data_pb2_grpc.py
locobuzz_protocol_buffer_python/grpc/protos/__init__.py
locobuzz_protocol_buffers_python-0.1.3.dist-info/METADATA
locobuzz_protocol_buffers_python-0.1.3.dist-info/WHEEL
locobuzz_protocol_buffers_python-0.1.3.dist-info/top_level.txt
locobuzz_protocol_buffers_python-0.1.3.dist-info/RECORD
