Metadata-Version: 2.1
Name: locobuzz_protocol_buffers_python
Version: 0.1.3
Summary: This package helps in to build the protocol buffers
Home-page: https://github.com/LocoBuzz-Solutions-Pvt-Ltd/locobuzz_protocols_buffers
Author: Sheikh Muhammed Shoaib
Author-email: shoaib.sheikh@locobuzz.com
Classifier: Programming Language :: Python :: 3
Classifier: License :: OSI Approved :: MIT License
Classifier: Operating System :: OS Independent
Requires-Python: >=3.9
Requires-Dist: Cython
Requires-Dist: grpcio
Requires-Dist: grpcio-tools
Requires-Dist: protobuf
